easycnn/__init__.py
easycnn/core.py
easycnn/exporter.py
easycnn/presets.py
easycnn/visualizer.py
litecnn/__init__.py
litecnn/core.py
litecnn/exporter.py
litecnn/presets.py
litecnn/visualizer.py
litecnn-1.0.3.dist-info/licenses/LICENSE
litecnn-1.0.3.dist-info/METADATA
litecnn-1.0.3.dist-info/WHEEL
litecnn-1.0.3.dist-info/entry_points.txt
litecnn-1.0.3.dist-info/top_level.txt
litecnn-1.0.3.dist-info/RECORD
