Metadata-Version: 2.4
Name: litecnn
Version: 1.0.3
Summary: LiteCNN: Intuitive Python library for creating, training and visualizing convolutional neural networks. Features simplified CNN layer definition, automated training workflows, model visualization, and seamless Keras-to-ONNX conversion. Includes 15 pre-configured popular models for immediate use.
Author: Gabriel Wiśniewski
Author-email: gabrys.wisniewski@op.pl
Project-URL: Documentation, https://github.com/Gabrli/EasyCNN---docs
Project-URL: Source Code, https://github.com/Gabrli/easyCNN
Keywords: deep-learning,cnn,neural-networks,tensorflow,keras,machine-learning,ai,computer-vision,image-processing,model-training,visualization,easy-to-use,python,convolutional-networks
Classifier: Programming Language :: Python :: 3
Classifier: License :: OSI Approved :: MIT License
Classifier: Operating System :: OS Independent
License-File: LICENSE
Requires-Dist: tensorflow
Requires-Dist: numpy
Requires-Dist: matplotlib
Requires-Dist: opencv-python
Requires-Dist: tf2onnx
Requires-Dist: onnx
Dynamic: author
Dynamic: author-email
Dynamic: classifier
Dynamic: description
Dynamic: description-content-type
Dynamic: keywords
Dynamic: license-file
Dynamic: project-url
Dynamic: requires-dist
Dynamic: summary
